_bo4e_python_version.py
bo4e/__init__.py
bo4e/py.typed
bo4e/version.py
bo4e/zusatzattribut.py
bo4e/bo/__init__.py
bo4e/bo/angebot.py
bo4e/bo/ausschreibung.py
bo4e/bo/bilanzierung.py
bo4e/bo/buendelvertrag.py
bo4e/bo/energiemenge.py
bo4e/bo/fremdkosten.py
bo4e/bo/geraet.py
bo4e/bo/geschaeftsobjekt.py
bo4e/bo/geschaeftspartner.py
bo4e/bo/kosten.py
bo4e/bo/lastgang.py
bo4e/bo/lokationszuordnung.py
bo4e/bo/marktlokation.py
bo4e/bo/marktteilnehmer.py
bo4e/bo/messlokation.py
bo4e/bo/netzlokation.py
bo4e/bo/person.py
bo4e/bo/preisblatt.py
bo4e/bo/preisblattdienstleistung.py
bo4e/bo/preisblatthardware.py
bo4e/bo/preisblattkonzessionsabgabe.py
bo4e/bo/preisblattmessung.py
bo4e/bo/preisblattnetznutzung.py
bo4e/bo/rechnung.py
bo4e/bo/region.py
bo4e/bo/regionaltarif.py
bo4e/bo/standorteigenschaften.py
bo4e/bo/steuerbareressource.py
bo4e/bo/tarif.py
bo4e/bo/tarifinfo.py
bo4e/bo/tarifkosten.py
bo4e/bo/tarifpreisblatt.py
bo4e/bo/technischeressource.py
bo4e/bo/vertrag.py
bo4e/bo/zaehler.py
bo4e/bo/zeitreihe.py
bo4e/com/__init__.py
bo4e/com/adresse.py
bo4e/com/angebotsposition.py
bo4e/com/angebotsteil.py
bo4e/com/angebotsvariante.py
bo4e/com/aufabschlag.py
bo4e/com/aufabschlagproort.py
bo4e/com/aufabschlagregional.py
bo4e/com/aufabschlagstaffelproort.py
bo4e/com/ausschreibungsdetail.py
bo4e/com/ausschreibungslos.py
bo4e/com/betrag.py
bo4e/com/com.py
bo4e/com/dienstleistung.py
bo4e/com/energieherkunft.py
bo4e/com/energiemix.py
bo4e/com/fremdkostenblock.py
bo4e/com/fremdkostenposition.py
bo4e/com/geokoordinaten.py
bo4e/com/katasteradresse.py
bo4e/com/konfigurationsprodukt.py
bo4e/com/kontaktweg.py
bo4e/com/konzessionsabgabe.py
bo4e/com/kostenblock.py
bo4e/com/kostenposition.py
bo4e/com/kriteriumwert.py
bo4e/com/lastprofil.py
bo4e/com/marktgebietinfo.py
bo4e/com/menge.py
bo4e/com/positionsaufabschlag.py
bo4e/com/preis.py
bo4e/com/preisgarantie.py
bo4e/com/preisposition.py
bo4e/com/preisstaffel.py
bo4e/com/rechnungsposition.py
bo4e/com/regionalegueltigkeit.py
bo4e-202501.0.0.dist-info/METADATA
bo4e-202501.0.0.dist-info/WHEEL
bo4e-202501.0.0.dist-info/licenses/AUTHORS.rst
bo4e-202501.0.0.dist-info/licenses/LICENSE.rst
bo4e-202501.0.0.dist-info/RECORD
