Metadata-Version: 2.4
Name: bo4e
Version: 202501.0.0
Summary: Python Library that implements the BO4E Standard.
Project-URL: Changelog, https://github.com/bo4e/bo4e-python/releases
Project-URL: Homepage, https://github.com/bo4e/bo4e-python
Project-URL: Documentation, https://bo4e-python.readthedocs.io/en/latest/
Author-email: Kevin Krechan <kevin.krechan@hochfrequenz.de>, Leon Haffmans <leon.haffmans@hochfrequenz.de>, Annika Schlögl <annika.schloegl@hochfrequenz.de>, Franziska Vesely <franziska.vesely@hochfrequenz.de>, Konstantin Klein <konstantin.klein@hochfrequenz.de>
License: MIT
License-File: AUTHORS.rst
License-File: LICENSE.rst
Keywords: bdew,bo4e,edi@energy
Classifier: Development Status :: 4 - Beta
Classifier: Intended Audience :: Developers
Classifier: License :: OSI Approved :: MIT License
Classifier: Operating System :: OS Independent
Classifier: Programming Language :: Python
Classifier: Programming Language :: Python :: 3 :: Only
Classifier: Programming Language :: Python :: 3.9
Classifier: Programming Language :: Python :: 3.10
Classifier: Programming Language :: Python :: 3.11
Classifier: Programming Language :: Python :: 3.12
Requires-Python: >=3.9
Requires-Dist: iso3166
Requires-Dist: pydantic>=2.0.0
Requires-Dist: pyhumps
